meltingplot/__init__.py
meltingplot/rpi_camera/__init__.py
meltingplot/rpi_camera/__main__.py
meltingplot/rpi_camera/_version.py
meltingplot/rpi_camera/server.py
meltingplot/rpi_camera/cli/__init__.py
meltingplot/rpi_camera/cli/install.py
meltingplot_rpi_camera-0.0.7.data/data/reboot_on_wifi_disconnect.sh
meltingplot_rpi_camera-0.0.7.data/data/rpi-camera.service
meltingplot_rpi_camera-0.0.7.dist-info/licenses/LICENSE
meltingplot_rpi_camera-0.0.7.dist-info/METADATA
meltingplot_rpi_camera-0.0.7.dist-info/WHEEL
meltingplot_rpi_camera-0.0.7.dist-info/entry_points.txt
meltingplot_rpi_camera-0.0.7.dist-info/top_level.txt
meltingplot_rpi_camera-0.0.7.dist-info/RECORD
