Metadata-Version: 2.4
Name: meltingplot.rpi_camera
Version: 0.0.7
Summary: RPi Camera MJPEG Streamer.
Home-page: 
Author: Tim Schneider
Author-email: tim@meltingplot.net
License:                                  Apache License
License-File: LICENSE
Requires-Dist: click
Requires-Dist: piexif
Provides-Extra: test
Requires-Dist: pytest-cov; extra == "test"
Requires-Dist: pytest-mock; extra == "test"
Requires-Dist: pytest-asyncio; extra == "test"
Requires-Dist: flake8; extra == "test"
Requires-Dist: flake8-import-order; extra == "test"
Requires-Dist: flake8-blind-except; extra == "test"
Requires-Dist: flake8-builtins; extra == "test"
Requires-Dist: flake8-docstrings; extra == "test"
Requires-Dist: flake8-bugbear; extra == "test"
Requires-Dist: flake8-comprehensions; extra == "test"
Requires-Dist: flake8-commas; extra == "test"
Requires-Dist: pep8-naming; extra == "test"
Requires-Dist: bandit; extra == "test"
Requires-Dist: yapf; extra == "test"
Requires-Dist: versioneer; extra == "test"
Requires-Dist: twine; extra == "test"
Dynamic: author
Dynamic: author-email
Dynamic: description
Dynamic: description-content-type
Dynamic: license
Dynamic: license-file
Dynamic: provides-extra
Dynamic: requires-dist
Dynamic: summary
